ai_training_utils/__init__.py
ai_training_utils/logging_helper.py
ai_training_utils/path_helper.py
ai_training_utils/singleton.py
ai_training_utils/tensorboard.py
ai_training_utils-0.0.7.dist-info/LICENSE
ai_training_utils-0.0.7.dist-info/METADATA
ai_training_utils-0.0.7.dist-info/WHEEL
ai_training_utils-0.0.7.dist-info/top_level.txt
ai_training_utils-0.0.7.dist-info/RECORD
