Metadata-Version: 2.1
Name: ai-training-utils
Version: 0.0.7
Summary: Utils to use while training AI models
Home-page: UNKNOWN
Author: Labs
Author-email: fn-labs@avisi.nl
License: UNKNOWN
Platform: UNKNOWN
Classifier: Programming Language :: Python :: 3
Classifier: License :: OSI Approved :: MIT License
Classifier: Operating System :: OS Independent
Requires-Python: >=3.7
Requires-Dist: tensorboard
